MANIFEST.in
README.md
setup.py
./sumake.egg-info/PKG-INFO
./sumake.egg-info/SOURCES.txt
./sumake.egg-info/dependency_links.txt
./sumake.egg-info/not-zip-safe
./sumake.egg-info/requires.txt
./sumake.egg-info/top_level.txt
bin/sumake
src/aws.mk
src/docker.mk
src/help.txt
src/ssh.mk
src/sumake
src/utils.mk
src/utils.py
sumake.egg-info/SOURCES.txt
test/test_setup.py