Metadata-Version: 2.1
Name: sumake
Version: 0.3.4
Summary: A generic makefile for projects.
Home-page: https://github.com/SuCicada/sumake
Author: SuCicada
Author-email: pengyifu@gmail.com
Requires-Dist: setuptools
